setup.py
mytranslator/__init__.py
mytranslator/translate.py
mytranslator.egg-info/PKG-INFO
mytranslator.egg-info/SOURCES.txt
mytranslator.egg-info/dependency_links.txt
mytranslator.egg-info/entry_points.txt
mytranslator.egg-info/top_level.txt