Metadata-Version: 1.0
Name: mytranslator
Version: 1.0.1
Summary: Simple translator in English and Chinese, easier to use
Home-page: https://github.com/guoruibiao/MyTranslator
Author: UNKNOWN
Author-email: UNKNOWN
License: MIT
Platform: UNKNOWN
